datasette_auth_headers/__init__.py
datasette_auth_headers-0.1.0.dist-info/LICENSE
datasette_auth_headers-0.1.0.dist-info/METADATA
datasette_auth_headers-0.1.0.dist-info/WHEEL
datasette_auth_headers-0.1.0.dist-info/entry_points.txt
datasette_auth_headers-0.1.0.dist-info/top_level.txt
datasette_auth_headers-0.1.0.dist-info/RECORD
