Metadata-Version: 2.1
Name: datasette-auth-headers
Version: 0.1.0
Summary: Authenticate a Datasette instance using headers set by an upstream proxy
Author: Abigail Pain
License: Apache-2.0
Project-URL: Homepage, https://github.com/codemicro/datasette-auth-headers
Project-URL: Changelog, https://github.com/codemicro/datasette-auth-headers/releases
Project-URL: Issues, https://github.com/codemicro/datasette-auth-headers/issues
Project-URL: CI, https://github.com/codemicro/datasette-auth-headers/actions
Classifier: Framework :: Datasette
Classifier: License :: OSI Approved :: Apache Software License
Requires-Python: >=3.9
License-File: LICENSE
Requires-Dist: datasette
Provides-Extra: test
Requires-Dist: pytest; extra == "test"
Requires-Dist: pytest-asyncio; extra == "test"
